st_card_component_elliot/__init__.py
st_card_component_elliot/frontend/build/asset-manifest.json
st_card_component_elliot/frontend/build/index.html
st_card_component_elliot/frontend/build/precache-manifest.b024b67afa5bc32e188488702ca5a717.js
st_card_component_elliot/frontend/build/service-worker.js
st_card_component_elliot/frontend/build/static/js/2.9c7d7d97.chunk.js
st_card_component_elliot/frontend/build/static/js/2.9c7d7d97.chunk.js.LICENSE.txt
st_card_component_elliot/frontend/build/static/js/2.9c7d7d97.chunk.js.map
st_card_component_elliot/frontend/build/static/js/main.6d185def.chunk.js
st_card_component_elliot/frontend/build/static/js/main.6d185def.chunk.js.map
st_card_component_elliot/frontend/build/static/js/runtime-main.44d30fc2.js
st_card_component_elliot/frontend/build/static/js/runtime-main.44d30fc2.js.map
st_card_component_elliot-0.0.1.dist-info/LICENSE
st_card_component_elliot-0.0.1.dist-info/METADATA
st_card_component_elliot-0.0.1.dist-info/WHEEL
st_card_component_elliot-0.0.1.dist-info/top_level.txt
st_card_component_elliot-0.0.1.dist-info/RECORD
